django_amazon_ses.py
django_amazon_ses-4.0.1.dist-info/LICENSE.txt
django_amazon_ses-4.0.1.dist-info/METADATA
django_amazon_ses-4.0.1.dist-info/WHEEL
django_amazon_ses-4.0.1.dist-info/top_level.txt
django_amazon_ses-4.0.1.dist-info/RECORD
