Metadata-Version: 2.1
Name: django-amazon-ses
Version: 4.0.1
Summary: A Django email backend that uses Boto3 to interact with Amazon Simple Email Service (SES).
Home-page: https://github.com/azavea/django-amazon-ses
Author: Hector Castro
Author-email: hcastro@azavea.com
License: Apache License 2.0
Keywords: amazon,django,email,ses
Platform: UNKNOWN
Classifier: Development Status :: 5 - Production/Stable
Classifier: Framework :: Django
Classifier: Framework :: Django :: 2.2
Classifier: Intended Audience :: Developers
Classifier: License :: OSI Approved :: Apache Software License
Classifier: Programming Language :: Python
Classifier: Programming Language :: Python :: 3
Classifier: Programming Language :: Python :: 3 :: Only
Classifier: Programming Language :: Python :: 3.7
Classifier: Programming Language :: Python :: 3.8
Classifier: Programming Language :: Python :: 3.9
Classifier: Programming Language :: Python :: 3.10
Requires-Python: >=3.7
License-File: LICENSE.txt
